[
  {
    "inputs": [
      { "internalType": "string", "name": "_name", "type": "string" },
      { "internalType": "string", "name": "_ipfsHash", "type": "string" },
      {
        "internalType": "uint256[]",
        "name": "milestoneAmounts",
        "type": "uint256[]"
      }
    ],
    "name": "applyForGrant",
    "outputs": [],
    "stateMutability": "nonpayable",
    "type": "function"
  },
  {
    "inputs": [
      { "internalType": "uint256", "name": "grantId", "type": "uint256" },
      { "internalType": "string", "name": "ipfsHash", "type": "string" }
    ],
    "name": "applyForGrantMilestone",
    "outputs": [],
    "stateMutability": "nonpayable",
    "type": "function"
  },
  {
    "inputs": [
      { "internalType": "uint256", "name": "_grantId", "type": "uint256" },
      { "internalType": "bool", "name": "approve", "type": "bool" }
    ],
    "name": "approveOrRejectGrant",
    "outputs": [],
    "stateMutability": "nonpayable",
    "type": "function"
  },
  {
    "inputs": [
      { "internalType": "uint256", "name": "grantId", "type": "uint256" },
      { "internalType": "bool", "name": "approve", "type": "bool" }
    ],
    "name": "approveOrRejectMilestone",
    "outputs": [],
    "stateMutability": "nonpayable",
    "type": "function"
  },
  {
    "inputs": [
      { "internalType": "uint256", "name": "_grantId", "type": "uint256" }
    ],
    "name": "cancelGrant",
    "outputs": [],
    "stateMutability": "nonpayable",
    "type": "function"
  },
  {
    "inputs": [
      {
        "internalType": "address",
        "name": "_newDaoMultisig",
        "type": "address"
      }
    ],
    "name": "changeDaoAddress",
    "outputs": [],
    "stateMutability": "nonpayable",
    "type": "function"
  },
  {
    "inputs": [
      { "internalType": "address", "name": "_daoMultisig", "type": "address" },
      {
        "internalType": "address",
        "name": "_ubeTokenAddress",
        "type": "address"
      }
    ],
    "stateMutability": "nonpayable",
    "type": "constructor"
  },
  {
    "anonymous": false,
    "inputs": [
      {
        "indexed": false,
        "internalType": "uint256",
        "name": "grantId",
        "type": "uint256"
      },
      {
        "indexed": false,
        "internalType": "uint256[]",
        "name": "milestoneAmounts",
        "type": "uint256[]"
      },
      {
        "indexed": false,
        "internalType": "address",
        "name": "creator",
        "type": "address"
      },
      {
        "indexed": false,
        "internalType": "string",
        "name": "ipfsHash",
        "type": "string"
      }
    ],
    "name": "GrantCreated",
    "type": "event"
  },
  {
    "anonymous": false,
    "inputs": [
      {
        "indexed": false,
        "internalType": "uint256",
        "name": "grantId",
        "type": "uint256"
      },
      {
        "indexed": false,
        "internalType": "uint256",
        "name": "milestoneId",
        "type": "uint256"
      },
      {
        "indexed": false,
        "internalType": "uint256",
        "name": "amount",
        "type": "uint256"
      },
      {
        "indexed": false,
        "internalType": "string",
        "name": "ipfsHash",
        "type": "string"
      },
      {
        "indexed": false,
        "internalType": "bool",
        "name": "approved",
        "type": "bool"
      }
    ],
    "name": "GrantMilestone",
    "type": "event"
  },
  {
    "anonymous": false,
    "inputs": [
      {
        "indexed": false,
        "internalType": "uint256",
        "name": "grantId",
        "type": "uint256"
      },
      {
        "indexed": false,
        "internalType": "uint256",
        "name": "state",
        "type": "uint256"
      }
    ],
    "name": "GrantState",
    "type": "event"
  },
  {
    "anonymous": false,
    "inputs": [
      {
        "indexed": true,
        "internalType": "address",
        "name": "previousOwner",
        "type": "address"
      },
      {
        "indexed": true,
        "internalType": "address",
        "name": "newOwner",
        "type": "address"
      }
    ],
    "name": "OwnershipTransferred",
    "type": "event"
  },
  {
    "inputs": [],
    "name": "renounceOwnership",
    "outputs": [],
    "stateMutability": "nonpayable",
    "type": "function"
  },
  {
    "inputs": [
      { "internalType": "address", "name": "newOwner", "type": "address" }
    ],
    "name": "transferOwnership",
    "outputs": [],
    "stateMutability": "nonpayable",
    "type": "function"
  },
  {
    "inputs": [],
    "name": "daoMultisig",
    "outputs": [{ "internalType": "address", "name": "", "type": "address" }],
    "stateMutability": "view",
    "type": "function"
  },
  {
    "inputs": [
      { "internalType": "uint256", "name": "grantId", "type": "uint256" }
    ],
    "name": "getGrant",
    "outputs": [
      {
        "components": [
          { "internalType": "uint256", "name": "id", "type": "uint256" },
          { "internalType": "string", "name": "name", "type": "string" },
          { "internalType": "address", "name": "grantee", "type": "address" },
          { "internalType": "string", "name": "ipfsHash", "type": "string" },
          {
            "internalType": "enum UbeGrants.State",
            "name": "state",
            "type": "uint8"
          },
          {
            "internalType": "uint256",
            "name": "nextPayout",
            "type": "uint256"
          },
          {
            "internalType": "uint256",
            "name": "totalAmount",
            "type": "uint256"
          },
          {
            "internalType": "uint256[]",
            "name": "milestoneAmounts",
            "type": "uint256[]"
          },
          {
            "internalType": "string[]",
            "name": "milestoneDeliveries",
            "type": "string[]"
          }
        ],
        "internalType": "struct UbeGrants.Grant",
        "name": "",
        "type": "tuple"
      }
    ],
    "stateMutability": "view",
    "type": "function"
  },
  {
    "inputs": [{ "internalType": "uint256", "name": "", "type": "uint256" }],
    "name": "grants",
    "outputs": [
      { "internalType": "uint256", "name": "id", "type": "uint256" },
      { "internalType": "string", "name": "name", "type": "string" },
      { "internalType": "address", "name": "grantee", "type": "address" },
      { "internalType": "string", "name": "ipfsHash", "type": "string" },
      {
        "internalType": "enum UbeGrants.State",
        "name": "state",
        "type": "uint8"
      },
      { "internalType": "uint256", "name": "nextPayout", "type": "uint256" },
      { "internalType": "uint256", "name": "totalAmount", "type": "uint256" }
    ],
    "stateMutability": "view",
    "type": "function"
  },
  {
    "inputs": [],
    "name": "owner",
    "outputs": [{ "internalType": "address", "name": "", "type": "address" }],
    "stateMutability": "view",
    "type": "function"
  },
  {
    "inputs": [],
    "name": "ubeTokenAddress",
    "outputs": [{ "internalType": "address", "name": "", "type": "address" }],
    "stateMutability": "view",
    "type": "function"
  }
]
